lazyssh/__init__.py
lazyssh/__main__.py
lazyssh/command_mode.py
lazyssh/config.py
lazyssh/console_instance.py
lazyssh/logging_module.py
lazyssh/models.py
lazyssh/plugin_manager.py
lazyssh/scp_mode.py
lazyssh/ssh.py
lazyssh/ui.py
lazyssh/plugins/.gitignore
lazyssh/plugins/__init__.py
lazyssh/plugins/_enumeration_plan.py
lazyssh/plugins/enumerate.py
lazyssh-1.6.2.dist-info/METADATA
lazyssh-1.6.2.dist-info/WHEEL
lazyssh-1.6.2.dist-info/entry_points.txt
lazyssh-1.6.2.dist-info/licenses/LICENSE
lazyssh-1.6.2.dist-info/RECORD
