Metadata-Version: 2.4
Name: lazyssh
Version: 1.6.2
Summary: A comprehensive SSH toolkit for managing connections and tunnels
Project-URL: Homepage, https://github.com/Bochner/lazyssh
Project-URL: Bug Tracker, https://github.com/Bochner/lazyssh/issues
Project-URL: Documentation, https://github.com/Bochner/lazyssh
Project-URL: Source Code, https://github.com/Bochner/lazyssh
Author-email: Bochner <lazyssh@example.com>
License-Expression: MIT
License-File: LICENSE
Keywords: connection,management,proxy,socks,ssh,terminal,tunnel
Classifier: Development Status :: 5 - Production/Stable
Classifier: Environment :: Console
Classifier: Intended Audience :: Developers
Classifier: Intended Audience :: System Administrators
Classifier: Operating System :: MacOS
Classifier: Operating System :: POSIX :: Linux
Classifier: Programming Language :: Python :: 3
Classifier: Programming Language :: Python :: 3.11
Classifier: Programming Language :: Python :: 3.12
Classifier: Programming Language :: Python :: 3.13
Classifier: Topic :: System :: Networking
Classifier: Topic :: System :: Systems Administration
Requires-Python: >=3.11
Requires-Dist: art>=5.9
Requires-Dist: click>=8.0.0
Requires-Dist: colorama>=0.4.6
Requires-Dist: paramiko>=3.0.0
Requires-Dist: pexpect>=4.8.0
Requires-Dist: prompt-toolkit<3.1.0,>=3.0.39
Requires-Dist: python-dotenv>=1.0.0
Requires-Dist: rich>=13.0.0
Requires-Dist: tomli-w>=1.0.0
Requires-Dist: wcwidth>=0.2.5
